{
  "version": "1.0.0",
  "restore": {
    "projectUniqueName": "/Users/henryezeanya/Projects/DevCodes/Monivault/src/Monivault.EntityFrameworkCore/Monivault.EntityFrameworkCore.csproj",
    "projectName": "Monivault.EntityFrameworkCore",
    "projectPath": "/Users/henryezeanya/Projects/DevCodes/Monivault/src/Monivault.EntityFrameworkCore/Monivault.EntityFrameworkCore.csproj",
    "outputPath": "/Users/henryezeanya/Projects/DevCodes/Monivault/src/Monivault.EntityFrameworkCore/obj/",
    "projectStyle": "PackageReference",
    "fallbackFolders": [
      "/usr/local/share/dotnet/sdk/NuGetFallbackFolder"
    ],
    "originalTargetFrameworks": [
      "netcoreapp2.2"
    ],
    "sources": {
      "https://api.nuget.org/v3/index.json": {}
    },
    "frameworks": {
      "netcoreapp2.2": {
        "projectReferences": {
          "/Users/henryezeanya/Projects/DevCodes/Monivault/src/Monivault.Core/Monivault.Core.csproj": {
            "projectPath": "/Users/henryezeanya/Projects/DevCodes/Monivault/src/Monivault.Core/Monivault.Core.csproj"
          }
        }
      }
    },
    "warningProperties": {
      "warnAsError": [
        "NU1605"
      ]
    }
  },
  "frameworks": {
    "netcoreapp2.2": {
      "dependencies": {
        "Microsoft.EntityFrameworkCore.Design": {
          "target": "Package",
          "version": "[2.2.1, )"
        },
        "Microsoft.EntityFrameworkCore.SqlServer": {
          "target": "Package",
          "version": "[2.2.1, )"
        },
        "Microsoft.EntityFrameworkCore.Tools": {
          "include": "Runtime, Build, Native, ContentFiles, Analyzers",
          "suppressParent": "All",
          "target": "Package",
          "version": "[2.2.1, )"
        },
        "Microsoft.NETCore.App": {
          "suppressParent": "All",
          "target": "Package",
          "version": "[2.2.0, )",
          "autoReferenced": true
        }
      },
      "imports": [
        "portable-net45+win8+wp8+wpa81",
        "net461"
      ],
      "assetTargetFallback": true,
      "warn": true
    }
  }
}